kellog/__init__.py
kellog/_kellog.py
kellog-1.0.1.dist-info/LICENSE
kellog-1.0.1.dist-info/METADATA
kellog-1.0.1.dist-info/WHEEL
kellog-1.0.1.dist-info/top_level.txt
kellog-1.0.1.dist-info/RECORD
