Metadata-Version: 2.1
Name: kellog
Version: 1.0.1
Summary: Easy logging
Author-email: celynw <3299161+celynw@users.noreply.github.com>
License: GNU GENERAL PUBLIC LICENSE
Project-URL: Repository, https://github.com/celynw/kellog
Project-URL: Issues, https://github.com/celynw/kellog/issues
Project-URL: Changelog, https://github.com/celynw/kellog/blob/master/CHANGELOG.md
Keywords: log,print,color,pretty
Classifier: Development Status :: 4 - Beta
Classifier: Environment :: Console
Classifier: Intended Audience :: Developers
Classifier: License :: OSI Approved :: GNU General Public License v3 (GPLv3)
Classifier: Natural Language :: English
Classifier: Topic :: System :: Logging
Classifier: Programming Language :: Python :: 3
Classifier: Programming Language :: Python :: 3.7
Classifier: Programming Language :: Python :: 3.8
Classifier: Programming Language :: Python :: 3.9
Classifier: Programming Language :: Python :: 3.10
Classifier: Programming Language :: Python :: 3.11
Classifier: Programming Language :: Python :: 3.12
Requires-Python: >=3.7
License-File: LICENSE
Requires-Dist: colorama
Requires-Dist: ujson
Requires-Dist: munch
Requires-Dist: typing-extensions
Provides-Extra: dev
Requires-Dist: ruff ; extra == 'dev'
Requires-Dist: mypy ; extra == 'dev'
Requires-Dist: pytest ; extra == 'dev'
Requires-Dist: colored-traceback ; extra == 'dev'
